czy_ip_acquirer_mcp/__init__.py
czy_ip_acquirer_mcp-0.1.0.dist-info/METADATA
czy_ip_acquirer_mcp-0.1.0.dist-info/WHEEL
czy_ip_acquirer_mcp-0.1.0.dist-info/entry_points.txt
czy_ip_acquirer_mcp-0.1.0.dist-info/RECORD
