Metadata-Version: 2.4
Name: czy-ip-acquirer-mcp
Version: 0.1.0
Summary: Add your description here
Author-email: Adam <chenzhengyifr@gmail.com>
Requires-Python: >=3.13
Requires-Dist: mcp[cli]>=1.9.4
